opay_python/__init__.py
opay_python/opay_client.py
opay_python/util.py
opay_python-0.0.3.dist-info/LICENSE
opay_python-0.0.3.dist-info/METADATA
opay_python-0.0.3.dist-info/WHEEL
opay_python-0.0.3.dist-info/top_level.txt
opay_python-0.0.3.dist-info/RECORD
