Metadata-Version: 2.1
Name: opay-python
Version: 0.0.3
Summary: A Python client for the OPay API
Author-email: Isaac Robert <isaacrobertoluwaseun@gmail.com>
Project-URL: Homepage, https://github.com/isaacrobert33/OPay-python
Project-URL: Bug Tracker, https://github.com/isaacrobert33/OPay-python/issues
Classifier: Programming Language :: Python :: 3
Classifier: License :: OSI Approved :: MIT License
Classifier: Operating System :: OS Independent
Requires-Python: >=3.7
License-File: LICENSE
